is_number_priyatham/__init__.py
is_number_priyatham/_version.py
is_number_priyatham/is_number.py
is_number_priyatham-0.0.2.dist-info/LICENSE
is_number_priyatham-0.0.2.dist-info/METADATA
is_number_priyatham-0.0.2.dist-info/WHEEL
is_number_priyatham-0.0.2.dist-info/top_level.txt
is_number_priyatham-0.0.2.dist-info/RECORD
