Metadata-Version: 2.1
Name: is-number-priyatham
Version: 0.0.2
Summary: A Python library to determine if something is a number.
Home-page: UNKNOWN
Author: Priyatham
Author-email: kunarapuriyatham@gmail.com
License: UNKNOWN
Platform: UNKNOWN
Classifier: Programming Language :: Python :: 3
Classifier: License :: OSI Approved :: MIT License
Classifier: Operating System :: OS Independent
Requires-Python: >=3.6
Requires-Dist: requests (==2.22.0)
